zope.app.onlinehelp-5.0-py3.11-nspkg.pth
zope/app/onlinehelp/DEPENDENCIES.cfg
zope/app/onlinehelp/SETUP.cfg
zope/app/onlinehelp/__init__.py
zope/app/onlinehelp/configure.zcml
zope/app/onlinehelp/ftesting.zcml
zope/app/onlinehelp/interfaces.py
zope/app/onlinehelp/meta.zcml
zope/app/onlinehelp/metaconfigure.py
zope/app/onlinehelp/metadirectives.py
zope/app/onlinehelp/onlinehelp-configure.zcml
zope/app/onlinehelp/onlinehelp-meta.zcml
zope/app/onlinehelp/onlinehelp.py
zope/app/onlinehelp/onlinehelptopic.py
zope/app/onlinehelp/testing.py
zope/app/onlinehelp/browser/__init__.py
zope/app/onlinehelp/browser/configure.zcml
zope/app/onlinehelp/browser/helptopic.pt
zope/app/onlinehelp/browser/item.gif
zope/app/onlinehelp/browser/minus.gif
zope/app/onlinehelp/browser/onlinehelp.css
zope/app/onlinehelp/browser/onlinehelp_macros.pt
zope/app/onlinehelp/browser/onlinehelp_navigation_macros.pt
zope/app/onlinehelp/browser/plus.gif
zope/app/onlinehelp/browser/tests.py
zope/app/onlinehelp/browser/tree.css
zope/app/onlinehelp/browser/tree.js
zope/app/onlinehelp/browser/tree.py
zope/app/onlinehelp/help/README.stx
zope/app/onlinehelp/help/__init__.py
zope/app/onlinehelp/help/configure.zcml
zope/app/onlinehelp/help/developer.txt
zope/app/onlinehelp/help/mgmt-main-1.png
zope/app/onlinehelp/help/samples.txt
zope/app/onlinehelp/help/ui.stx
zope/app/onlinehelp/help/welcome.stx
zope/app/onlinehelp/tests/__init__.py
zope/app/onlinehelp/tests/help.html
zope/app/onlinehelp/tests/help.pt
zope/app/onlinehelp/tests/help.rst
zope/app/onlinehelp/tests/help.stx
zope/app/onlinehelp/tests/help.txt
zope/app/onlinehelp/tests/help.zcml
zope/app/onlinehelp/tests/help2.txt
zope/app/onlinehelp/tests/test1.png
zope/app/onlinehelp/tests/test2.png
zope/app/onlinehelp/tests/test_helpdirectives.py
zope/app/onlinehelp/tests/test_onlinehelp.py
zope/app/onlinehelp/tests/test_treeview.py
zope/app/onlinehelp/tests/util.py
zope/app/onlinehelp/tests/output/test1.xml
zope/app/onlinehelp/tests/output/test2.xml
zope.app.onlinehelp-5.0.dist-info/METADATA
zope.app.onlinehelp-5.0.dist-info/WHEEL
zope.app.onlinehelp-5.0.dist-info/namespace_packages.txt
zope.app.onlinehelp-5.0.dist-info/top_level.txt
zope.app.onlinehelp-5.0.dist-info/RECORD
