Metadata-Version: 2.1
Name: zope.app.onlinehelp
Version: 5.0
Summary: Framework for Context-Sensitive Help Pages
Home-page: http://github.com/zopefoundation/zope.app.onlinehelp
Author: Zope Foundation and Contributors
Author-email: zope-dev@zope.org
License: ZPL 2.1
Keywords: zope3 online help
Classifier: Development Status :: 5 - Production/Stable
Classifier: Environment :: Web Environment
Classifier: Intended Audience :: Developers
Classifier: License :: OSI Approved :: Zope Public License
Classifier: Programming Language :: Python
Classifier: Programming Language :: Python :: 3
Classifier: Programming Language :: Python :: 3.7
Classifier: Programming Language :: Python :: 3.8
Classifier: Programming Language :: Python :: 3.9
Classifier: Programming Language :: Python :: 3.10
Classifier: Programming Language :: Python :: 3.11
Classifier: Programming Language :: Python :: Implementation :: CPython
Classifier: Programming Language :: Python :: Implementation :: PyPy
Classifier: Natural Language :: English
Classifier: Operating System :: OS Independent
Classifier: Topic :: Internet :: WWW/HTTP
Classifier: Framework :: Zope :: 3
Requires-Dist: persistent
Requires-Dist: setuptools
Requires-Dist: zope.app.component
Requires-Dist: zope.app.file (>=4.0.0)
Requires-Dist: zope.app.pagetemplate (>=4.0.0)
Requires-Dist: zope.app.publication (>=4.2.1)
Requires-Dist: zope.app.security (>=4.0.0)
Requires-Dist: zope.component
Requires-Dist: zope.configuration
Requires-Dist: zope.container
Requires-Dist: zope.contenttype
Requires-Dist: zope.i18n
Requires-Dist: zope.interface
Requires-Dist: zope.location
Requires-Dist: zope.publisher (>=4.3.1)
Requires-Dist: zope.schema
Requires-Dist: zope.security (>=4.1.1)
Requires-Dist: zope.testing
Requires-Dist: zope.traversing
Provides-Extra: docs
Requires-Dist: Sphinx ; extra == 'docs'
Requires-Dist: repoze.sphinx.autointerface ; extra == 'docs'
Requires-Dist: sphinx-rtd-theme ; extra == 'docs'
Provides-Extra: test
Requires-Dist: webtest ; extra == 'test'
Requires-Dist: zope.app.basicskin (>=4.0.0) ; extra == 'test'
Requires-Dist: zope.app.folder ; extra == 'test'
Requires-Dist: zope.app.http ; extra == 'test'
Requires-Dist: zope.app.authentication (>=4.0.0) ; extra == 'test'
Requires-Dist: zope.app.principalannotation ; extra == 'test'
Requires-Dist: zope.app.preference (>=4.0.0) ; extra == 'test'
Requires-Dist: zope.app.renderer (>=4.0.0) ; extra == 'test'
Requires-Dist: zope.app.rotterdam (>=4.0.0) ; extra == 'test'
Requires-Dist: zope.app.wsgi ; extra == 'test'
Requires-Dist: zope.annotation ; extra == 'test'
Requires-Dist: zope.copypastemove ; extra == 'test'
Requires-Dist: zope.configuration ; extra == 'test'
Requires-Dist: zope.formlib ; extra == 'test'
Requires-Dist: zope.login ; extra == 'test'
Requires-Dist: zope.principalannotation ; extra == 'test'
Requires-Dist: zope.securitypolicy ; extra == 'test'
Requires-Dist: zope.site ; extra == 'test'
Requires-Dist: zope.testing ; extra == 'test'
Requires-Dist: zope.testrunner ; extra == 'test'
